LICENSE
MANIFEST.in
README.rst
setup.py
django_oauth_toolkit_fork.egg-info/PKG-INFO
django_oauth_toolkit_fork.egg-info/SOURCES.txt
django_oauth_toolkit_fork.egg-info/dependency_links.txt
django_oauth_toolkit_fork.egg-info/not-zip-safe
django_oauth_toolkit_fork.egg-info/requires.txt
django_oauth_toolkit_fork.egg-info/top_level.txt
oauth2_provider/__init__.py
oauth2_provider/admin.py
oauth2_provider/backends.py
oauth2_provider/compat.py
oauth2_provider/compat_handlers.py
oauth2_provider/constants.py
oauth2_provider/decorators.py
oauth2_provider/exceptions.py
oauth2_provider/forms.py
oauth2_provider/generators.py
oauth2_provider/http.py
oauth2_provider/middleware.py
oauth2_provider/models.py
oauth2_provider/oauth2_backends.py
oauth2_provider/oauth2_validators.py
oauth2_provider/settings.py
oauth2_provider/urls.py
oauth2_provider/validators.py
oauth2_provider/ext/__init__.py
oauth2_provider/ext/rest_framework/__init__.py
oauth2_provider/ext/rest_framework/authentication.py
oauth2_provider/ext/rest_framework/permissions.py
oauth2_provider/migrations/0001_initial.py
oauth2_provider/migrations/0002_08_updates.py
oauth2_provider/migrations/0003_add_application_grant_types.py
oauth2_provider/migrations/__init__.py
oauth2_provider/south_migrations/0001_initial.py
oauth2_provider/south_migrations/0002_adding_indexes.py
oauth2_provider/south_migrations/0003_auto__add_field_application_skip_authorization__chg_field_accesstoken_.py
oauth2_provider/south_migrations/__init__.py
oauth2_provider/templates/404.html
oauth2_provider/templates/oauth2_provider/application_confirm_delete.html
oauth2_provider/templates/oauth2_provider/application_detail.html
oauth2_provider/templates/oauth2_provider/application_form.html
oauth2_provider/templates/oauth2_provider/application_list.html
oauth2_provider/templates/oauth2_provider/application_registration_form.html
oauth2_provider/templates/oauth2_provider/authorize.html
oauth2_provider/templates/oauth2_provider/base.html
oauth2_provider/templatetags/__init__.py
oauth2_provider/templatetags/compat.py
oauth2_provider/tests/__init__.py
oauth2_provider/tests/models.py
oauth2_provider/tests/settings.py
oauth2_provider/tests/test_application_views.py
oauth2_provider/tests/test_auth_backends.py
