Metadata-Version: 1.1
Name: django-oauth-toolkit-fork
Version: 0.11.0
Summary: Fork of django-oauth-toolkit
Home-page: https://github.com/ulule/django-oauth-toolkit
Author: Federico Frenguelli, Massimiliano Pippi
Author-email: synasius@gmail.com, mpippi@gmail.com
License: BSD
Keywords: django oauth oauth2 oauthlib
Platform: UNKNOWN
Classifier: Development Status :: 4 - Beta
Classifier: Environment :: Web Environment
Classifier: Framework :: Django
Classifier: License :: OSI Approved :: BSD License
Classifier: Operating System :: OS Independent
Classifier: Programming Language :: Python :: 2.6
Classifier: Programming Language :: Python :: 2.7
Classifier: Programming Language :: Python :: 3.3
Classifier: Programming Language :: Python :: 3.4
Classifier: Topic :: Software Development :: Libraries :: Python Modules
Classifier: Framework :: Django
Classifier: Framework :: Django :: 1.4
Classifier: Framework :: Django :: 1.5
Classifier: Framework :: Django :: 1.6
Classifier: Framework :: Django :: 1.7
